Metadata-Version: 2.4
Name: agent2agent
Version: 0.1.65
Summary: A platform for building and deploying AI agents with structured skills
Home-page: https://github.com/rosaboyle/airtrain.dev
Author: Dheeraj Pai
Author-email: Dheeraj Pai <helloworldcmu@gmail.com>
Project-URL: Homepage, https://github.com/rosaboyle/airtrain.dev
Project-URL: Documentation, https://docs.airtrain.dev/
Classifier: Development Status :: 3 - Alpha
Classifier: Intended Audience :: Developers
Classifier: License :: OSI Approved :: MIT License
Classifier: Operating System :: OS Independent
Classifier: Programming Language :: Python :: 3
Classifier: Programming Language :: Python :: 3.8
Classifier: Programming Language :: Python :: 3.9
Classifier: Programming Language :: Python :: 3.10
Requires-Python: >=3.8
Requires-Dist: pydantic>=2.10.6
Requires-Dist: openai>=1.60.1
Requires-Dist: python-dotenv>=1.0.1
Requires-Dist: PyYAML>=6.0.2
Requires-Dist: firebase-admin>=6.6.0
Requires-Dist: loguru>=0.7.3
Requires-Dist: requests>=2.32.3
Requires-Dist: boto3>=1.36.6
Requires-Dist: together>=1.3.13
Requires-Dist: anthropic>=0.45.0
Requires-Dist: groq>=0.15.0
Requires-Dist: cerebras-cloud-sdk>=1.19.0
Requires-Dist: google-genai>=1.0.0
Requires-Dist: fireworks-ai>=0.15.12
Requires-Dist: google-generativeai>=0.8.4
Requires-Dist: click>=8.0.0
Requires-Dist: rich>=13.3.1
Requires-Dist: prompt-toolkit>=3.0.36
Requires-Dist: colorama>=0.4.6
Requires-Dist: typer>=0.9.0
Requires-Dist: posthog>=3.7.0
Provides-Extra: dev
Requires-Dist: black>=24.10.0; extra == "dev"
Requires-Dist: flake8>=7.1.1; extra == "dev"
Requires-Dist: isort>=5.13.0; extra == "dev"
Requires-Dist: mypy>=1.9.0; extra == "dev"
Requires-Dist: pytest>=7.0.0; extra == "dev"
Requires-Dist: twine>=4.0.0; extra == "dev"
Requires-Dist: build>=0.10.0; extra == "dev"
Requires-Dist: types-PyYAML>=6.0; extra == "dev"
Requires-Dist: types-requests>=2.31.0; extra == "dev"
Requires-Dist: types-Markdown>=3.5.0; extra == "dev"
Requires-Dist: toml>=0.10.2; extra == "dev"
Dynamic: author
Dynamic: home-page
Dynamic: requires-python
